phone_number_validator_test/__init__.py
phone_number_validator_test/validator.py
phone_number_validator_test-0.1.1.dist-info/METADATA
phone_number_validator_test-0.1.1.dist-info/WHEEL
phone_number_validator_test-0.1.1.dist-info/RECORD
