Metadata-Version: 2.1
Name: phone_number_validator_test
Version: 0.1.1
Summary: 
Author: Himanshu Srivastava
Author-email: himanshu.srivastava@bik.ai
Requires-Python: >=3.10,<4.0
Classifier: Programming Language :: Python :: 3
Classifier: Programming Language :: Python :: 3.10
Classifier: Programming Language :: Python :: 3.11
Classifier: Programming Language :: Python :: 3.12
Requires-Dist: requests (>=2.32.3,<3.0.0)
